LICENSE
MANIFEST.in
README.rst
setup.py
pygreppy/__init__.py
pygreppy/codegen.py
pygreppy/core.py
pygreppy.egg-info/PKG-INFO
pygreppy.egg-info/SOURCES.txt
pygreppy.egg-info/dependency_links.txt
pygreppy.egg-info/entry_points.txt
pygreppy.egg-info/not-zip-safe
pygreppy.egg-info/requires.txt
pygreppy.egg-info/top_level.txt