Metadata-Version: 1.2
Name: pygreppy
Version: 1.0.0
Summary: Tool for searching in python source code
Home-page: https://github.com/skvoter/pygreppy
Author: Kirill Korovin
Author-email: skvoter46@gmail.com
License: BSD
Platform: UNKNOWN
Classifier: Development Status :: 5 - Production/Stable
Classifier: License :: OSI Approved :: BSD License
Classifier: Programming Language :: Python :: 3 :: Only
Classifier: Topic :: Text Processing :: Filters
Classifier: Topic :: Text Processing :: General
Requires-Python: >=3
